{
  "sessions": {
    "default": {
      "summary": "User asked for a three‑word greeting.",
      "traits": [
        "concise",
        "straightforward"
      ],
      "needs": [
        "brief greeting"
      ],
      "boundaries": [],
      "attachmentGuess": "neutral",
      "readiness": null,
      "lastUpdated": "2026-03-03T23:32:44.409Z"
    },
    "onboarding-debug": {
      "summary": "",
      "traits": [],
      "needs": [],
      "boundaries": [],
      "attachmentGuess": "",
      "readiness": null,
      "previousQuestions": [
        "Hey, I’m your Soulmap guide. What’s your name?",
        "Nice to meet you, Patel! What kind of fighting do you enjoy most—martial arts, sports, or something else?"
      ],
      "lastUpdated": "2026-03-03T23:36:53.277Z"
    },
    "platform-test": {
      "summary": "Meet from Mumbai identifies dishonesty as a dealbreaker, indicating a strong value placed on honesty.",
      "traits": [],
      "needs": [
        "honesty"
      ],
      "boundaries": [],
      "attachmentGuess": "Secure",
      "readiness": 0,
      "previousQuestions": [],
      "lastUpdated": "2026-03-03T23:40:08.824Z"
    },
    "onboarding-v7do3jsq": {
      "summary": "",
      "traits": [],
      "needs": [],
      "boundaries": [],
      "attachmentGuess": "",
      "readiness": null,
      "previousQuestions": [
        "Hey, I'm your Soulmap guide. What's your name?",
        "Alright, I get that vibe. What name should I call you?",
        "Got it, Meet. Does that feel right?",
        "That’s solid, Meet. Fight or flight — which one shows up?",
        "That's someone who leans in. What pattern repeats in your love life?",
        "That's a lot of self-awareness. What do you truly need versus settle for?"
      ],
      "lastUpdated": "2026-03-03T23:42:31.368Z"
    }
  }
}